Metadata-Version: 1.0
Name: Bl2seqWrapperCW
Version: 0.1
Summary: Program for blast two sequences
Home-page: http://github.com/wanglabtongji/Bl2seqWrapperCW
Author: wanglabtongji
Author-email: 08chenfeiwang@tongji.edu.cn
License: MIT
Platform: UNKNOWN
